<?xml version="1.0" encoding="UTF-8"?>
<beans xmlns="http://www.springframework.org/schema/beans"
	xmlns:xsi="http://www.w3.org/2001/XMLSchema-instance"
	xsi:schemaLocation="
        http://www.springframework.org/schema/beans http://www.springframework.org/schema/beans/spring-beans.xsd">
	<bean class="com.jspiders.spring1.bean.FatherBean" name="father1">
		<property name="Id" value="1"></property>
		<property name="Name" value="Messi"></property>
		<property name="children">
			<list>
				<bean class="com.jspiders.spring1.bean.ChildBean" name="child1">
					<property name="Id" value="1"></property>
					<property name="Name" value="ronaldo"></property>
				</bean>
				<bean class="com.jspiders.spring1.bean.ChildBean" name="child2">
					<property name="Id" value="2"></property>
					<property name="Name" value="Mbappe"></property>
				</bean>
			</list>
		</property>
	</bean>

</beans>